{
  "name": "Calm Days, Sober Nights - Day",
  "type": "light",
  "semanticHighlighting": true,
  "colors": {
    "focusBorder": "#58556B26",
    "sash.hoverBorder": "#00000035",
    "foreground": "#58556B",
    "descriptionForeground": "#716D85",
    "icon.foreground": "#58556B",
    "errorForeground": "#CF344D",
    "dropdown.foreground": "#58556B",
    "inputValidation.errorBackground": "#CF6578",
    "inputValidation.errorForeground": "#ffffffC6",
    "inputValidation.errorBorder": "#CF6578",
    "inputValidation.infoBackground": "#65BCCF",
    "inputValidation.infoForeground": "#ffffffC6",
    "inputValidation.infoBorder": "#65BCCF",
    "inputValidation.warningBackground": "#E69971",
    "inputValidation.warningForeground": "#ffffffc6",
    "inputValidation.warningBorder": "#E69971",
    "scrollbarSlider.background": "#0000001a",
    "scrollbarSlider.activeBackground": "#0000004d",
    "scrollbarSlider.hoverBackground": "#00000033",
    "progressBar.background": "#F14441",
    "list.activeSelectionBackground": "#00000010",
    "list.activeSelectionForeground": "#000000",
    "list.dropBackground": "#E1DFEDB3",
    "list.focusBackground": "#00000012",
    "list.focusForeground": "#000000",
    "list.focusOutline": "#00000018",
    "list.highlightForeground": "#6ABDAE",
    "list.hoverBackground": "#00000006",
    "list.hoverForeground": "#000000",
    "list.inactiveSelectionBackground": "#00000009",
    "list.inactiveSelectionForeground": "#000000",
    "list.inactiveFocusBackground": "#00000011",
    "list.invalidItemForeground": "#CF344D",
    "listFilterWidget.outline": "#E4D9FA",
    "listFilterWidget.background": "#E4D9FA",
    "listFilterWidget.noMatchesOutline": "#CF344D",
    "list.filterMatchBackground": "#76789318",
    "activityBar.dropBackground": "#E3E1EDB3",
    "editorGroup.border": "#1917241a",
    "editorGroup.dropBackground": "#E3E1EDB3",
    "editorGroupHeader.noTabsBackground": "#EDEBF5",
    "editor.wordHighlightBackground": "#736C9414",
    "editor.wordHighlightStrongBackground": "#736C9416",
    "editor.selectionBackground": "#6059801d",
    "editor.selectionHighlightBackground": "#00000008",
    "editor.inactiveSelectionBackground": "#60598008",
    "editor.findMatchBackground": "#76789318",
    "editor.findMatchHighlightBackground": "#736C9414",
    "editor.findRangeHighlightBackground": "#736C9409",
    "editor.hoverHighlightBackground": "#664D8C09",
    "editorLink.activeForeground": "#3fa6d9",
    "editor.rangeHighlightBackground": "#00000007",
    "editorWhitespace.foreground": "#00000016",
    "editorCodeLens.foreground": "#6C667A66",
    "editorBracketMatch.background": "#00000016",
    "editorBracketMatch.border": "#00000016",
    "editorOverviewRuler.border": "#00000000",
    "editorOverviewRuler.findMatchForeground": "#76789380",
    "editorOverviewRuler.rangeHighlightForeground": "#00000016",
    "editorOverviewRuler.selectionHighlightForeground": "#0000004F",
    "editorOverviewRuler.modifiedForeground": "#1A9494D3",
    "editorOverviewRuler.addedForeground": "#1A9C32D3",
    "editorOverviewRuler.deletedForeground": "#654E93D3",
    "editorOverviewRuler.errorForeground": "#CF344DD3",
    "editorOverviewRuler.warningForeground": "#CF6A34D3",
    "editorOverviewRuler.infoForeground": "#2D9CB5D3",
    "editorOverviewRuler.unicodeForeground": "#CF8634D3",
    "editorError.foreground": "#CF344D",
    "editorWarning.foreground": "#CF6A34",
    "editorInfo.foreground": "#2D9CB5",
    "list.errorForeground": "#CF344D",
    "list.warningForeground": "#CF6A34",
    "minimap.errorHighlight": "#CF344DB3",
    "minimap.warningHighlight": "#CF6A34B3",
    "minimap.selectionHighlight": "#6059804D",
    "minimap.findMatchHighlight": "#767893E6",
    "minimap.unicodeHighlight": "#CF8634B3",
    "editorUnicodeHighlight.border": "#CF863466",
    "editorGutter.modifiedBackground": "#1A9494B3",
    "editorGutter.addedBackground": "#1A9C32B3",
    "editorGutter.deletedBackground": "#654E93B3",
    "diffEditor.insertedTextBackground": "#1A9C321a",
    "diffEditor.removedTextBackground": "#654E931a",
    "debugExceptionWidget.background": "#E93D46",
    "debugExceptionWidget.border": "#E93D46",
    "editorMarkerNavigation.background": "#EDEBF5",
    "editorMarkerNavigationError.background": "#CF344D",
    "editorMarkerNavigationWarning.background": "#CF6A34",
    "editorMarkerNavigationInfo.background": "#2D9CB5",
    "problemsErrorIcon.foreground": "#CF344D",
    "problemsWarningIcon.foreground": "#CF6A34",
    "problemsInfoIcon.foreground": "#2D9CB5",
    "peekView.border": "#E1DFED",
    "peekViewEditor.background": "#EDEBF5",
    "peekViewEditorGutter.background": "#EDEBF5",
    "peekViewEditor.matchHighlightBackground": "#76789322",
    "peekViewResult.background": "#EBE9F5",
    "peekViewResult.fileForeground": "#58556B",
    "peekViewResult.lineForeground": "#58556B",
    "peekViewResult.matchHighlightBackground": "#76789330",
    "peekViewResult.selectionBackground": "#0000001a",
    "peekViewResult.selectionForeground": "#58556B",
    "peekViewTitle.background": "#F2F0FA",
    "peekViewTitleDescription.foreground": "#575361A7",
    "peekViewTitleLabel.foreground": "#5D5A68",
    "merge.currentHeaderBackground": "#7BE0E05E",
    "merge.currentContentBackground": "#7BE0E01a",
    "merge.incomingHeaderBackground": "#7DE8915E",
    "merge.incomingContentBackground": "#7DE8911a",
    "merge.border": "#00000009",
    "editorOverviewRuler.currentContentForeground": "#7BE0E06a",
    "editorOverviewRuler.incomingContentForeground": "#7DE8916a",
    "statusBar.foreground": "#000000A0",
    "statusBar.background": "#6ABDAE",
    "statusBar.border": "#00000026",
    "statusBar.debuggingForeground": "#FFC7E4",
    "statusBar.debuggingBackground": "#D14F93",
    "statusBar.debuggingBorder": "#00000030",
    "statusBarItem.activeBackground": "#00000020",
    "statusBarItem.hoverBackground": "#00000010",
    "statusBarItem.prominentBackground": "#0000004A",
    "statusBarItem.prominentForeground": "#ffffff",
    "statusBarItem.remoteForeground": "#BEABD1",
    "statusBarItem.remoteBackground": "#7657C2",
    "statusBarItem.remoteBorder": "#00000026",
    "statusBar.noFolderForeground": "#0000006B",
    "statusBar.noFolderBackground": "#F4F2FA",
    "statusBar.noFolderBorder": "#00000048",
    "notificationToast.border": "#C3C1CF",
    "notifications.border": "#58556B28",
    "notificationLink.foreground": "#3fa6d9",
    "extensionButton.prominentForeground": "#FFFFFFC8",
    "extensionButton.prominentBackground": "#BD4583",
    "extensionButton.prominentHoverBackground": "#A33C72",
    "pickerGroup.border": "#58556B30",
    "pickerGroup.foreground": "#565563",
    "terminal.selectionBackground": "#6059801a",
    "welcomePage.buttonBackground": "#00000010",
    "welcomePage.buttonHoverBackground": "#0000001A",
    "welcomePage.tileBackground": "#00000010",
    "welcomePage.tileHoverBackground": "#6ABDAE20",
    "walkThrough.embeddedEditorBackground": "#EDEDED",
    "gitDecoration.untrackedResourceForeground": "#1A9C32",
    "gitDecoration.addedResourceForeground": "#4A8216",
    "gitDecoration.modifiedResourceForeground": "#1A9494",
    "gitDecoration.stageModifiedResourceForeground": "#157A7A",
    "gitDecoration.deletedResourceForeground": "#523C69",
    "gitDecoration.stageDeletedResourceForeground": "#3E2D4F",
    "gitDecoration.ignoredResourceForeground": "#7E7A99",
    "gitDecoration.conflictingResourceForeground": "#9C211A",
    "gitDecoration.renamedResourceForeground": "#1B945B",
    "editor.background": "#EFEDF7",
    "editorGutter.background": "#EFEDF7",
    "breadcrumb.background": "#F2F0FA",
    "breadcrumb.foreground": "#9994B3",
    "breadcrumb.focusForeground": "#58556B",
    "breadcrumb.activeSelectionForeground": "#000000",
    "breadcrumbPicker.background": "#EBE9F5",
    "sideBarSectionHeader.background": "#EBE9F5",
    "sideBarSectionHeader.border": "#C8C5D4",
    "selection.background": "#664D8C20",
    "sideBar.background": "#EBE9F5",
    "sideBar.foreground": "#58556B",
    "sideBarSectionHeader.foreground": "#58556B",
    "activityBar.background": "#F2F0FA",
    "activityBar.border": "#C8C5D4",
    "activityBar.inactiveForeground": "#9994B3",
    "editorIndentGuide.activeBackground": "#9994B330",
    "editorIndentGuide.background": "#58556B08",
    "editorRuler.foreground": "#58556B09",
    "tree.indentGuidesStroke": "#58556B30",
    "editorSuggestWidget.background": "#EAE9F2",
    "editorSuggestWidget.foreground": "#9994B3",
    "editorSuggestWidget.border": "#58556B30",
    "editorSuggestWidget.selectedBackground": "#9994B330",
    "editorLineNumber.foreground": "#9994B375",
    "editorLineNumber.activeForeground": "#0000006f",
    "editor.lineHighlightBackground": "#58556B06",
    "editor.lineHighlightBorder": "#58556B08",
    "editorHint.foreground": "#58556B",
    "notifications.background": "#EBE9F5",
    "notifications.foreground": "#58556B",
    "button.foreground": "#000000A0",
    "button.background": "#6ABDAE",
    "button.hoverBackground": "#5CA396",
    "button.secondaryBackground": "#6ABDAE20",
    "button.secondaryHoverBackground": "#5CA39636",
    "button.secondaryForeground": "#4B857A",
    "titleBar.activeBackground": "#E6E4F0",
    "titleBar.inactiveBackground": "#F2F0FA",
    "titleBar.activeForeground": "#58556B",
    "titleBar.inactiveForeground": "#918EA1",
    "titleBar.border": "#9794A3",
    "editorGroupHeader.tabsBackground": "#F2F0FA",
    "editorGroupHeader.border": "#C8C5D4",
    "editorGroupHeader.tabsBorder": "#F2F0FA",
    "tab.border": "#F2F0FA",
    "tab.inactiveForeground": "#9994B3",
    "tab.inactiveBackground": "#F2F0FA",
    "tab.activeForeground": "#58556B",
    "tab.activeBackground": "#F2F0FA",
    "tab.hoverForeground": "#58556B",
    "tab.hoverBackground": "#EBE9F5",
    "tab.unfocusedActiveForeground": "#AAA4BF",
    "tab.unfocusedInactiveForeground": "#AAA4BF",
    "tab.unfocusedHoverForeground": "#75738C",
    "panel.border": "#58556B1a",
    "panel.background": "#EDEBF5",
    "terminal.background": "#EDEBF5",
    "sideBar.border": "#C8C5D4",
    "panelTitle.inactiveForeground": "#9994B3",
    "panelTitle.activeForeground": "#58556B",
    "input.background": "#E6E4F0",
    "input.border": "#58556B09",
    "inputOption.activeBackground": "#00000018",
    "inputOption.hoverBackground": "#00000010",
    "checkbox.background": "#EBE9F5",
    "editor.foreground": "#58556B",
    "sideBarTitle.foreground": "#58556B",
    "dropdown.background": "#E6E4F0",
    "dropdown.listBackground": "#E6E4F0",
    "dropdown.border": "#58556B10",
    "menubar.selectionForeground": "#FFFFFF",
    "menubar.selectionBackground": "#9994B320",
    "menu.background": "#EFEDF7",
    "menu.foreground": "#58556BC0",
    "menu.border": "#58556B30",
    "menu.separatorBackground": "#58556B30",
    "menu.selectionForeground": "#53525E",
    "menu.selectionBackground": "#9994B330",
    "scrollbar.shadow": "#9994B360",
    "widget.shadow": "#9994B360",
    "settings.headerForeground": "#58556B",
    "editorHoverWidget.background": "#EAE9F2",
    "editorHoverWidget.foreground": "#58556B",
    "editorHoverWidget.border": "#58556B30",
    "editorHoverWidget.statusBarBackground": "#E5E4ED",
    "checkbox.foreground": "#6ABDAE",
    "quickInput.background": "#EBE9F5",
    "quickInput.foreground": "#58556B",
    "input.foreground": "#58556B",
    "input.placeholderForeground": "#807E8F90",
    "terminal.foreground": "#58556B",
    "terminal.ansiBlack": "#000000",
    "terminal.ansiRed": "#EB6C81",
    "terminal.ansiGreen": "#00B392",
    "terminal.ansiYellow": "#ED8045",
    "terminal.ansiBlue": "#2EBED1",
    "terminal.ansiMagenta": "#9175C7",
    "terminal.ansiCyan": "#46ba94",
    "terminal.ansiWhite": "#AAA5C2",
    "terminal.ansiBrightBlack": "#6C667A",
    "terminal.ansiBrightRed": "#F07186",
    "terminal.ansiBrightGreen": "#00B392",
    "terminal.ansiBrightYellow": "#F28449",
    "terminal.ansiBrightBlue": "#36C3D6",
    "terminal.ansiBrightMagenta": "#967ACC",
    "terminal.ansiBrightCyan": "#4cbf99",
    "terminal.ansiBrightWhite": "#CAC9D1",
    "editorWidget.background": "#EBE9F5",
    "editorWidget.border": "#58556B30",
    "editorWidget.foreground": "#9994B3",
    "badge.background": "#6FB37020",
    "badge.foreground": "#4B857A",
    "editorCursor.foreground": "#6ABDAE",
    "editorSuggestWidget.highlightForeground": "#6ABDAE",
    "editorWidget.resizeBorder": "#6ABDAE",
    "activityBar.activeBorder": "#6ABDAE",
    "activityBar.foreground": "#6ABDAE",
    "activityBarBadge.background": "#6ABDAE",
    "activityBarBadge.foreground": "#D6FFF7",
    "activityBar.activeBackground": "#6ABDAE12",
    "tab.activeBorder": "#6ABDAE",
    "panelTitle.activeBorder": "#6ABDAE",
    "panel.dropBorder": "#6ABDAE",
    "notificationCenterHeader.background": "#EBE9F5",
    "notificationCenterHeader.foreground": "#58556B",
    "notificationCenter.border": "#C3C1CF",
    "textLink.foreground": "#6ABDAE",
    "textLink.activeForeground": "#5CA396",
    "debugToolBar.background": "#E6E4F0",
    "debugToolBar.border": "#E6E4F0",
    "toolbar.hoverBackground": "#00000010",
    "toolbar.activeBackground": "#00000018",
    "settings.modifiedItemIndicator": "#1A9494",
    "settings.rowHoverBackground": "#00000007",
    "editorBracketPairGuide.activeBackground1": "#156873",
    "editorBracketHighlight.foreground1": "#156873",
    "editorBracketPairGuide.activeBackground2": "#00678C",
    "editorBracketHighlight.foreground2": "#00678C",
    "editorBracketPairGuide.activeBackground3": "#AD3F65",
    "editorBracketHighlight.foreground3": "#AD3F65",
    "editorBracketPairGuide.activeBackground4": "#007537",
    "editorBracketHighlight.foreground4": "#007537",
    "editorBracketHighlight.unexpectedBracket.foreground": "#B52D43",
    "editorLightBulb.foreground": "#CF7748",
    "editorLightBulbAutoFix.foreground": "#368E9C",
    "editorInlayHint.background": "#197F8C1B",
    "editorInlayHint.foreground": "#197F8CC1",
    "editor.snippetTabstopHighlightBackground": "#67627A10",
    "snippetFinalTabstopHighlightBackground": "#67627A1D"
  },
  "tokenColors": [
    {
      "settings": {
        "background": "#EFEDF7",
        "foreground": "#6C667A"
      }
    },
    {
      "name": "Braces",
      "scope": [
        "meta.brace.curly",
        "meta.brace.round",
        "meta.brace.square",
        "meta.structure.dictionary",
        "punctuation.section",
        "punctuation.definition.block",
        "punctuation.definition.parameters"
      ],
      "settings": {
        "foreground": "#6C667AB0"
      }
    },
    {
      "name": "Comment",
      "scope": ["comment"],
      "settings": {
        "fontStyle": "italic",
        "foreground": "#AAA5C2"
      }
    },
    {
      "name": "String",
      "scope": ["string", "constant.other.symbol"],
      "settings": {
        "foreground": "#F25F6B"
      }
    },
    {
      "name": "String Regexp",
      "scope": ["string.regexp"],
      "settings": {
        "foreground": "#F25F6B"
      }
    },
    {
      "name": "Regular Expressions",
      "scope": [
        "constant.character",
        "constant.other",
        "punctuation.definition.group.regexp"
      ],
      "settings": {
        "foreground": "#0AA877"
      }
    },
    {
      "name": "Escape Characters",
      "scope": ["constant.character.escape.backslash.regexp"],
      "settings": {
        "foreground": "#F14441"
      }
    },
    {
      "name": "Anchor Escape Characters",
      "scope": ["keyword.control.anchor.regexp"],
      "settings": {}
    },
    {
      "name": "Number",
      "scope": ["constant.numeric"],
      "settings": {
        "foreground": "#F14441"
      }
    },
    {
      "name": "Built-in constants",
      "scope": ["constant.language"],
      "settings": {
        "foreground": "#F14441"
      }
    },
    {
      "name": "Variable",
      "scope": ["variable"],
      "settings": {
        "foreground": "#6C667A"
      }
    },
    {
      "name": "Member Variable",
      "scope": ["variable.member"],
      "settings": {
        "foreground": "#C74874"
      }
    },
    {
      "name": "Storage",
      "scope": ["storage"],
      "settings": {
        "foreground": "#0071A1"
      }
    },
    {
      "name": "Keyword",
      "scope": ["keyword"],
      "settings": {
        "foreground": "#0071A1"
      }
    },
    {
      "name": "Operators",
      "scope": ["keyword.operator"],
      "settings": {
        "foreground": "#C74874"
      }
    },
    {
      "name": "Separators like ; or ,",
      "scope": [
        "punctuation.separator",
        "punctuation.terminator",
        "meta.delimiter.comma"
      ],
      "settings": {
        "foreground": "#6C667A96"
      }
    },
    {
      "name": "Accessor",
      "scope": ["punctuation.accessor"],
      "settings": {
        "foreground": "#C74874"
      }
    },
    {
      "name": "Types fixes",
      "scope": [
        "source.java storage.type",
        "source.haskell storage.type",
        "source.c storage.type",
        "meta.type.parameters"
      ],
      "settings": {
        "foreground": "#C74874"
      }
    },
    {
      "name": "Inherited class type",
      "scope": ["entity.other.inherited-class"],
      "settings": {
        "foreground": "#0F8771"
      }
    },
    {
      "name": "Lambda arrow",
      "scope": ["storage.type.function"],
      "settings": {
        "foreground": "#C74874"
      }
    },
    {
      "name": "Java primitive variable types",
      "scope": ["source.java storage.type.primitive"],
      "settings": {
        "foreground": "#0F8771"
      }
    },
    {
      "name": "Function name",
      "scope": ["entity.name.function"],
      "settings": {
        "foreground": "#197F8C"
      }
    },
    {
      "name": "Function arguments",
      "scope": ["variable.parameter", "meta.parameter"],
      "settings": {
        "foreground": "#7657C2"
      }
    },
    {
      "name": "Function call",
      "scope": [
        "variable.function",
        "variable.annotation",
        "meta.function-call.generic",
        "support.function.go"
      ],
      "settings": {
        "foreground": "#197F8C"
      }
    },
    {
      "name": "Library function",
      "scope": ["support.function", "support.macro"],
      "settings": {
        "foreground": "#00A39A",
        "fontStyle": "italic"
      }
    },
    {
      "name": "Imports and packages",
      "scope": ["entity.name.import", "entity.name.package"],
      "settings": {
        "foreground": "#F25F6B"
      }
    },
    {
      "name": "Object",
      "scope": ["string.unquoted", "meta.embedded"],
      "settings": {
        "foreground": "#4545A8"
      }
    },
    {
      "name": "Entity name",
      "scope": ["entity.name"],
      "settings": {
        "foreground": "#00A39A"
      }
    },
    {
      "name": "Static types",
      "scope": ["entity.name.type", "storage.type.cs"],
      "settings": { "foreground": "#0F8771" }
    },
    {
      "name": "Provided (support) values",
      "scope": "support",
      "settings": { "foreground": "#0F8771" }
    },
    {
      "name": "Tag",
      "scope": ["entity.name.tag", "meta.tag.sgml"],
      "settings": {
        "foreground": "#0F8771"
      }
    },
    {
      "name": "Tag start/end",
      "scope": [
        "punctuation.definition.tag.end",
        "punctuation.definition.tag.begin",
        "punctuation.definition.tag"
      ],
      "settings": {
        "foreground": "#0F877180"
      }
    },
    {
      "name": "Tag attribute",
      "scope": ["entity.other.attribute-name"],
      "settings": {
        "foreground": "#17717D"
      }
    },
    {
      "name": "Library constant",
      "scope": ["support.constant"],
      "settings": {
        "fontStyle": "italic",
        "foreground": "#C74874"
      }
    },
    {
      "name": "Library class/type",
      "scope": ["support.type", "support.class", "source.go storage.type"],
      "settings": {
        "foreground": "#00A39A"
      }
    },
    {
      "name": "Decorators/annotation",
      "scope": [
        "meta.decorator punctuation.decorator",
        "storage.type.annotation",
        "entity.name.class.decorator",
        "keyword.operator.decorator"
      ],
      "settings": {
        "foreground": "#CC8049"
      }
    },
    {
      "name": "Invalid",
      "scope": ["invalid"],
      "settings": {
        "foreground": "#CF344D"
      }
    },
    {
      "name": "diff.header",
      "scope": ["meta.diff", "meta.diff.header"],
      "settings": {
        "foreground": "#c594c5"
      }
    },
    {
      "name": "Ruby class methods",
      "scope": ["source.ruby variable.other.readwrite"],
      "settings": {
        "foreground": "#197F8C"
      }
    },
    {
      "name": "CSS tag names",
      "scope": [
        "source.css entity.name.tag",
        "source.sass entity.name.tag",
        "source.scss entity.name.tag",
        "source.less entity.name.tag",
        "source.stylus entity.name.tag"
      ],
      "settings": {
        "foreground": "#C74874"
      }
    },
    {
      "name": "CSS browser prefix",
      "scope": [
        "source.css support.type",
        "source.sass support.type",
        "source.scss support.type",
        "source.less support.type",
        "source.stylus support.type"
      ],
      "settings": {
        "foreground": "#AAA5C2"
      }
    },
    {
      "name": "CSS Properties",
      "scope": ["support.type.property-name"],
      "settings": {
        "fontStyle": "normal",
        "foreground": "#0F8771"
      }
    },
    {
      "name": "Search Results Nums",
      "scope": ["constant.numeric.line-number.find-in-files - match"],
      "settings": {
        "foreground": "#AAA5C2"
      }
    },
    {
      "name": "Search Results Match Nums",
      "scope": ["constant.numeric.line-number.match"],
      "settings": {
        "foreground": "#0071A1"
      }
    },
    {
      "name": "Search Results Lines",
      "scope": ["entity.name.filename.find-in-files"],
      "settings": {
        "foreground": "#F25F6B"
      }
    },
    {
      "scope": ["message.error"],
      "settings": {
        "foreground": "#ff3333"
      }
    },
    {
      "name": "Language variable",
      "scope": ["variable.language"],
      "settings": {
        "fontStyle": "italic",
        "foreground": "#0F8771"
      }
    },
    {
      "name": "Markup heading",
      "scope": ["markup.heading", "markup.heading entity.name"],
      "settings": {
        "fontStyle": "bold",
        "foreground": "#F25F6B"
      }
    },
    {
      "name": "Markup links",
      "scope": ["markup.underline.link", "string.other.link"],
      "settings": {
        "foreground": "#0F8771"
      }
    },
    {
      "name": "Markup Italic",
      "scope": ["markup.italic"],
      "settings": {
        "fontStyle": "italic",
        "foreground": "#C74874"
      }
    },
    {
      "name": "Markup Bold",
      "scope": ["markup.bold"],
      "settings": {
        "fontStyle": "bold",
        "foreground": "#C74874"
      }
    },
    {
      "name": "Markup Bold/italic",
      "scope": ["markup.italic markup.bold", "markup.bold markup.italic"],
      "settings": {
        "fontStyle": "bold italic"
      }
    },
    {
      "name": "Markup Code",
      "scope": ["markup.raw"],
      "settings": {
        "background": "#6C667A05"
      }
    },
    {
      "name": "Markup Code Inline",
      "scope": ["markup.raw.inline"],
      "settings": {
        "background": "#6C667A0f"
      }
    },
    {
      "name": "Markdown Separator",
      "scope": ["meta.separator"],
      "settings": {
        "fontStyle": "bold",
        "background": "#6C667A0f",
        "foreground": "#AAA5C2"
      }
    },
    {
      "name": "Markup Blockquote",
      "scope": ["markup.quote"],
      "settings": {
        "foreground": "#9E3C78",
        "fontStyle": "italic"
      }
    },
    {
      "name": "Markup List Bullet",
      "scope": ["markup.list punctuation.definition.list.begin"],
      "settings": {
        "foreground": "#197F8C"
      }
    },
    {
      "name": "Markup added",
      "scope": ["markup.inserted"],
      "settings": {
        "foreground": "#1A9C32"
      }
    },
    {
      "name": "Markup modified",
      "scope": ["markup.changed"],
      "settings": {
        "foreground": "#77a8d9"
      }
    },
    {
      "name": "Markup removed",
      "scope": ["markup.deleted"],
      "settings": {
        "foreground": "#654E93"
      }
    },
    {
      "name": "Markup Strike",
      "scope": ["markup.strike"],
      "settings": {
        "foreground": "#D1B170"
      }
    },
    {
      "name": "Markup Table",
      "scope": ["markup.table"],
      "settings": {
        "background": "#6C667A0f",
        "foreground": "#0F8771"
      }
    },
    {
      "name": "Markup Raw Inline",
      "scope": ["text.html.markdown markup.inline.raw"],
      "settings": {
        "foreground": "#C74874"
      }
    },
    {
      "name": "Markdown - Line Break",
      "scope": ["text.html.markdown meta.dummy.line-break"],
      "settings": {
        "background": "#AAA5C2",
        "foreground": "#AAA5C2"
      }
    },
    {
      "name": "Markdown - Raw Block Fenced",
      "scope": ["punctuation.definition.markdown"],
      "settings": {
        "background": "#6C667A",
        "foreground": "#AAA5C2"
      }
    },
    {
      "scope": [
        "constant.language",
        "keyword.control",
        "keyword.operator.expression",
        "keyword.other",
        "keyword.operator.new",
        "storage",
        "storage.type",
        "keyword.generator.asterisk.js"
      ],
      "settings": {
        "fontStyle": "bold"
      }
    },
    {
      "scope": ["entity.other.attribute-name"],
      "settings": {
        "fontStyle": "italic"
      }
    },
    {
      "scope": [
        "entity.name.function",
        "variable.parameter",
        "markup.quote",
        "source.elixir .punctuation.binary.elixir",
        "comment",
        "variable.language",
        "punctuation.definition.tag"
      ],
      "settings": {
        "fontStyle": "italic"
      }
    },
    {
      "scope": ["variable.language"],
      "settings": {
        "fontStyle": "bold"
      }
    },
    {
      "scope": ["storage.type.function.arrow"],
      "settings": {
        "fontStyle": ""
      }
    }
  ],
  "semanticTokenColors": {
    "variable.defaultLibrary": {
      "foreground": "#00A39A"
    },
    "property.declaration": {
      "foreground": "#4545A8"
    }
  }
}
